MANIFEST.in
setup.py
zpy2html
src/zippydoc/__init__.py
src/zippydoc/block_markup.py
src/zippydoc/document.py
src/zippydoc/transformation_ruleset.py
src/zippydoc/value.py
src/zippydoc/data/template.html
zippydoc.egg-info/PKG-INFO
zippydoc.egg-info/SOURCES.txt
zippydoc.egg-info/dependency_links.txt
zippydoc.egg-info/requires.txt
zippydoc.egg-info/top_level.txt