Metadata-Version: 1.0
Name: zippydoc
Version: 1.2
Summary: Documentation markup language and library, including HTML converter.
Home-page: http://www.cryto.net/zippydoc
Author: Sven Slootweg
Author-email: admin@cryto.net
License: UNKNOWN
Platform: UNKNOWN
